[
    {
        "question": "This is the time between classes when students can play. What is it? / Đây là thời gian giữa các tiết học khi học sinh có thể vui chơi. Nó là gì?",
        "options": [
            "Break time",
            "Class time",
            "Lunch time",
            "Home time"
        ],
        "correctAnswer": "Break time"
    },
    {
        "question": "This is a game you play with a black and white board and special pieces. What is it? / Đây là một trò chơi bạn chơi với một bàn cờ đen trắng và các quân cờ đặc biệt. Nó là gì?",
        "options": [
            "Chess",
            "Football",
            "Badminton",
            "Hide-and-seek"
        ],
        "correctAnswer": "Chess"
    },
    {
        "question": "This is a sport where you kick a ball into a goal. What is it? / Đây là một môn thể thao mà bạn đá một quả bóng vào khung thành. Nó là gì?",
        "options": [
            "Football",
            "Chess",
            "Badminton",
            "Skipping"
        ],
        "correctAnswer": "Football"
    },
    {
        "question": "In this sport, you use a racket to hit a shuttlecock over a net. What is it? / Trong môn thể thao này, bạn dùng vợt để đánh một quả cầu qua lưới. Nó là gì?",
        "options": [
            "Badminton",
            "Football",
            "Chess",
            "Hide-and-seek"
        ],
        "correctAnswer": "Badminton"
    },
    {
        "question": "This is an activity where you jump over a rope. What is it? / Đây là một hoạt động mà bạn nhảy qua một sợi dây. Nó là gì?",
        "options": [
            "Skipping",
            "Playing",
            "Reading",
            "Singing"
        ],
        "correctAnswer": "Skipping"
    },
    {
        "question": "This is a game where one person closes their eyes and tries to find the others. What is it? / Đây là một trò chơi mà một người nhắm mắt và cố gắng tìm những người khác. Nó là gì?",
        "options": [
            "Hide-and-seek",
            "Chess",
            "Football",
            "Badminton"
        ],
        "correctAnswer": "Hide-and-seek"
    },
    {
        "question": "What are you doing? - I'm ____ a book about animals. / Bạn đang làm gì vậy? - Tớ đang ____ một cuốn sách về động vật.",
        "options": [
            "reading",
            "playing",
            "singing",
            "dancing"
        ],
        "correctAnswer": "reading"
    },
    {
        "question": "To ask what someone is doing, you say: / Để hỏi ai đó đang làm gì, bạn nói:",
        "options": [
            "What are you doing?",
            "What is your name?",
            "How are you?",
            "Do you like chess?"
        ],
        "correctAnswer": "What are you doing?"
    },
    {
        "question": "The correct answer to 'What are you doing?' could be: / Câu trả lời đúng cho 'What are you doing?' có thể là:",
        "options": [
            "I'm drawing a picture.",
            "My name is Nam.",
            "I'm fine, thank you.",
            "Yes, I do."
        ],
        "correctAnswer": "I'm drawing a picture."
    },
    {
        "question": "What do you call the things you do for fun? / Bạn gọi những việc bạn làm để giải trí là gì?",
        "options": [
            "Activities",
            "Homework",
            "Chores",
            "Lessons"
        ],
        "correctAnswer": "Activities"
    },
    {
        "question": "What is the opposite of 'boring'? / Từ trái nghĩa của 'boring' là gì?",
        "options": [
            "Fun",
            "Happy",
            "Exciting",
            "Good"
        ],
        "correctAnswer": "Fun"
    },
    {
        "question": "Playing with friends during break time is ____. / Chơi với bạn bè trong giờ giải lao thì ____.",
        "options": [
            "fun",
            "boring",
            "sad",
            "difficult"
        ],
        "correctAnswer": "fun"
    },
    {
        "question": "What do you need to play badminton? / Bạn cần gì để chơi cầu lông?",
        "options": [
            "A racket and a shuttlecock",
            "A ball and a goal",
            "A board and pieces",
            "A rope"
        ],
        "correctAnswer": "A racket and a shuttlecock"
    },
    {
        "question": "What do you call the action of talking with friends? / Bạn gọi hành động nói chuyện với bạn bè là gì?",
        "options": [
            "Chatting",
            "Reading",
            "Singing",
            "Sleeping"
        ],
        "correctAnswer": "Chatting"
    },
    {
        "question": "What is the opposite of 'start'? / Từ trái nghĩa của 'start' là gì?",
        "options": [
            "Finish",
            "Begin",
            "Go",
            "End"
        ],
        "correctAnswer": "Finish"
    },
    {
        "question": "Spell the word for the game with a black and white board. / Đánh vần từ chỉ trò chơi với bàn cờ đen trắng.",
        "options": [
            "c-h-e-s-s",
            "c-h-e-e-s-e",
            "c-h-e-s-t",
            "c-h-e-c-k"
        ],
        "correctAnswer": "c-h-e-s-s"
    },
    {
        "question": "What is the opposite of 'many'? / Từ trái nghĩa của 'many' là gì?",
        "options": [
            "Few",
            "Some",
            "All",
            "None"
        ],
        "correctAnswer": "Few"
    },
    {
        "question": "There are ____ students playing in the yard. / Có ____ học sinh đang chơi trong sân.",
        "options": [
            "many",
            "no",
            "sad",
            "old"
        ],
        "correctAnswer": "many"
    },
    {
        "question": "What do you call a game played on a table with paddles and a small ball? / Bạn gọi một trò chơi được chơi trên bàn với vợt và một quả bóng nhỏ là gì?",
        "options": [
            "Table tennis",
            "Football",
            "Badminton",
            "Chess"
        ],
        "correctAnswer": "Table tennis"
    },
    {
        "question": "What is the opposite of 'love'? / Từ trái nghĩa của 'love' là gì?",
        "options": [
            "Hate",
            "Like",
            "Enjoy",
            "Want"
        ],
        "correctAnswer": "Hate"
    },
    {
        "question": "I ____ playing hide-and-seek with my friends. / Tôi ____ chơi trốn tìm với bạn bè của mình.",
        "options": [
            "like",
            "hate",
            "eat",
            "read"
        ],
        "correctAnswer": "like"
    },
    {
        "question": "Spell the word for the sport where you kick a ball. / Đánh vần từ chỉ môn thể thao mà bạn đá một quả bóng.",
        "options": [
            "f-o-o-t-b-a-l-l",
            "b-a-s-k-e-t-b-a-l-l",
            "t-e-n-n-i-s",
            "v-o-l-l-e-y-b-a-l-l"
        ],
        "correctAnswer": "f-o-o-t-b-a-l-l"
    },
    {
        "question": "What is the opposite of 'give'? / Từ trái nghĩa của 'give' là gì?",
        "options": [
            "Take",
            "Receive",
            "Buy",
            "Sell"
        ],
        "correctAnswer": "Take"
    },
    {
        "question": "You can ____ a ball and throw it to your friend. / Bạn có thể ____ một quả bóng và ném nó cho bạn của mình.",
        "options": [
            "catch",
            "give",
            "read",
            "eat"
        ],
        "correctAnswer": "catch"
    },
    {
        "question": "What do you call the object you hit in badminton? / Bạn gọi vật thể bạn đánh trong môn cầu lông là gì?",
        "options": [
            "A shuttlecock",
            "A ball",
            "A frisbee",
            "A racket"
        ],
        "correctAnswer": "A shuttlecock"
    },
    {
        "question": "Spell the word for the action of jumping over a rope. / Đánh vần từ chỉ hành động nhảy qua một sợi dây.",
        "options": [
            "s-k-i-p-p-i-n-g",
            "j-u-m-p-i-n-g",
            "r-u-n-n-i-n-g",
            "h-o-p-p-i-n-g"
        ],
        "correctAnswer": "s-k-i-p-p-i-n-g"
    },
    {
        "question": "What is the opposite of 'good'? / Từ trái nghĩa của 'good' là gì?",
        "options": [
            "Bad",
            "Nice",
            "Great",
            "Kind"
        ],
        "correctAnswer": "Bad"
    },
    {
        "question": "It is ____ to cheat in a game. / Thật ____ khi gian lận trong một trò chơi.",
        "options": [
            "bad",
            "good",
            "nice",
            "fun"
        ],
        "correctAnswer": "bad"
    },
    {
        "question": "What do you call a person you are playing against? / Bạn gọi một người đang chơi chống lại bạn là gì?",
        "options": [
            "An opponent",
            "A friend",
            "A teammate",
            "A classmate"
        ],
        "correctAnswer": "An opponent"
    },
    {
        "question": "Spell the word for a fun activity. / Đánh vần từ chỉ một hoạt động vui vẻ.",
        "options": [
            "g-a-m-e",
            "t-e-s-t",
            "w-o-r-k",
            "c-l-a-s-s"
        ],
        "correctAnswer": "g-a-m-e"
    },
    {
        "question": "What is the opposite of 'happy'? / Từ trái nghĩa của 'happy' là gì?",
        "options": [
            "Sad",
            "Angry",
            "Tired",
            "Hungry"
        ],
        "correctAnswer": "Sad"
    },
    {
        "question": "I feel ____ when I lose a game of chess. / Tôi cảm thấy ____ khi thua một ván cờ.",
        "options": [
            "sad",
            "happy",
            "excited",
            "hungry"
        ],
        "correctAnswer": "sad"
    },
    {
        "question": "What do you call the action of talking to friends in a relaxed way? / Bạn gọi hành động nói chuyện với bạn bè một cách thư giãn là gì?",
        "options": [
            "Chatting",
            "Shouting",
            "Whispering",
            "Arguing"
        ],
        "correctAnswer": "Chatting"
    },
    {
        "question": "Spell the word for the sport with a racket and shuttlecock. / Đánh vần từ chỉ môn thể thao với vợt và quả cầu.",
        "options": [
            "b-a-d-m-i-n-t-o-n",
            "t-e-n-n-i-s",
            "s-q-u-a-s-h",
            "p-i-n-g-p-o-n-g"
        ],
        "correctAnswer": "b-a-d-m-i-n-t-o-n"
    },
    {
        "question": "What is the opposite of 'beautiful'? / Từ trái nghĩa của 'beautiful' là gì?",
        "options": [
            "Ugly",
            "Pretty",
            "Nice",
            "Good"
        ],
        "correctAnswer": "Ugly"
    },
    {
        "question": "My friend's drawing is very ____. / Bức vẽ của bạn tôi rất ____.",
        "options": [
            "beautiful",
            "ugly",
            "sad",
            "old"
        ],
        "correctAnswer": "beautiful"
    },
    {
        "question": "What do you call the time when you don't have to study? / Bạn gọi thời gian khi bạn không phải học là gì?",
        "options": [
            "Free time",
            "Class time",
            "Work time",
            "Sleep time"
        ],
        "correctAnswer": "Free time"
    },
    {
        "question": "Spell the word for the game where you look for others. / Đánh vần từ chỉ trò chơi mà bạn tìm kiếm những người khác.",
        "options": [
            "h-i-d-e-a-n-d-s-e-e-k",
            "t-a-g",
            "c-h-a-s-e",
            "f-o-l-l-o-w"
        ],
        "correctAnswer": "h-i-d-e-a-n-d-s-e-e-k"
    }
]
